choose_next.py
choose_next-3.0.0.dist-info/LICENSE.txt
choose_next-3.0.0.dist-info/METADATA
choose_next-3.0.0.dist-info/WHEEL
choose_next-3.0.0.dist-info/entry_points.txt
choose_next-3.0.0.dist-info/top_level.txt
choose_next-3.0.0.dist-info/RECORD
